LICENSE
alipan/__init__.py
python_alipan-0.0.0.dist-info/LICENSE
python_alipan-0.0.0.dist-info/METADATA
python_alipan-0.0.0.dist-info/WHEEL
python_alipan-0.0.0.dist-info/RECORD
